LICENSE
MANIFEST.in
README.md
requirements.txt
setup.py
drf_madprops.egg-info/PKG-INFO
drf_madprops.egg-info/SOURCES.txt
drf_madprops.egg-info/dependency_links.txt
drf_madprops.egg-info/requires.txt
drf_madprops.egg-info/top_level.txt
madprops/__init__.py
madprops/serializers.py